wasabis3/__init__.py
wasabis3/cli.py
wasabis3/formatter.py
wasabis3/initializer.py
wasabis3/wasabi.py
wasabis3-1.0.0.dist-info/AUTHORS.rst
wasabis3-1.0.0.dist-info/LICENSE
wasabis3-1.0.0.dist-info/METADATA
wasabis3-1.0.0.dist-info/WHEEL
wasabis3-1.0.0.dist-info/entry_points.txt
wasabis3-1.0.0.dist-info/top_level.txt
wasabis3-1.0.0.dist-info/RECORD
