Metadata-Version: 2.1
Name: wasabis3
Version: 1.0.0
Summary: A suite of maintenance tools for Wasabi S3 buckets 
Home-page: https://github.com/salimdason/wasabis3
Author: Mohammed Salim Dason
Author-email: salimdason@outlook.com
License: GNU General Public License v3
Keywords: wasabis3
Classifier: Development Status :: 2 - Pre-Alpha
Classifier: Intended Audience :: Developers
Classifier: License :: OSI Approved :: GNU General Public License v3 (GPLv3)
Classifier: Natural Language :: English
Classifier: Programming Language :: Python :: 3
Classifier: Programming Language :: Python :: 3.6
Classifier: Programming Language :: Python :: 3.7
Classifier: Programming Language :: Python :: 3.8
Requires-Python: >=3.6
License-File: LICENSE
License-File: AUTHORS.rst
